sqlalchemy_geonames/__init__.py
sqlalchemy_geonames/_compat.py
sqlalchemy_geonames/files.py
sqlalchemy_geonames/imports.py
sqlalchemy_geonames/log.py
sqlalchemy_geonames/metadata.py
sqlalchemy_geonames/models.py
sqlalchemy_geonames/reader.py
sqlalchemy_geonames/settings.py
sqlalchemy_geonames/utils.py
sqlalchemy_geonames/bin/__init__.py
sqlalchemy_geonames/bin/sqlageonames.py
sqlalchemy_geonames-0.1.4.dist-info/DESCRIPTION.rst
sqlalchemy_geonames-0.1.4.dist-info/METADATA
sqlalchemy_geonames-0.1.4.dist-info/RECORD
sqlalchemy_geonames-0.1.4.dist-info/WHEEL
sqlalchemy_geonames-0.1.4.dist-info/entry_points.txt
sqlalchemy_geonames-0.1.4.dist-info/metadata.json
sqlalchemy_geonames-0.1.4.dist-info/top_level.txt
